terminal/__init__.py
terminal/cli.py
terminal/agents/__init__.py
terminal/agents/code_agent.py
terminal/agents/general_agent.py
terminal/agents/shell_agent.py
terminal/api/__init__.py
terminal/api/gemini.py
terminal/commands/__init__.py
terminal/commands/commands.py
terminal/commands/os_info.py
terminal/core/__init__.py
terminal/core/agent.py
terminal/core/executor.py
terminal/core/router.py
terminal/safety/__init__.py
terminal/safety/safety.py
terminal/utils/__init__.py
terminal/utils/config.py
terminal/utils/loading.py
terminal/utils/parsers.py
dwarp-0.1.7.dist-info/METADATA
dwarp-0.1.7.dist-info/WHEEL
dwarp-0.1.7.dist-info/entry_points.txt
dwarp-0.1.7.dist-info/top_level.txt
dwarp-0.1.7.dist-info/RECORD
