Metadata-Version: 2.4
Name: dwarp
Version: 0.1.7
Summary: Terminal assistant built as an open source minimal alternative to Warp
Author-email: Abhinav <abhinavkumarsingh2023@gmail.com>
License-Expression: MIT
Project-URL: Homepage, https://github.com/Abhinavexists/dwarp
Project-URL: Repository, https://github.com/Abhinavexists/dwarp.git
Project-URL: Issues, https://github.com/Abhinavexists/dwarp/issues
Keywords: terminal,ai,shell,assistant,cli,gemini
Classifier: Development Status :: 4 - Beta
Classifier: Intended Audience :: Developers
Classifier: Operating System :: POSIX :: Linux
Classifier: Programming Language :: Python :: 3
Classifier: Programming Language :: Python :: 3.12
Classifier: Topic :: System :: Shells
Classifier: Topic :: Utilities
Requires-Python: >=3.12
Requires-Dist: prompt-toolkit==3.0.51
Requires-Dist: rich==14.1.0
Requires-Dist: pydantic==2.11.7
Requires-Dist: python-dotenv==1.1.1
Requires-Dist: google-genai==1.31.0
